setup.py
andy_package_demo/__init__.py
andy_package_demo/hello.py
andy_package_demo.egg-info/PKG-INFO
andy_package_demo.egg-info/SOURCES.txt
andy_package_demo.egg-info/dependency_links.txt
andy_package_demo.egg-info/top_level.txt