Metadata-Version: 2.1
Name: andy-package-demo
Version: 0.1
Summary: Andy Package Demo
Author: yaozhiqiang
Author-email: 1141338015@qq.com
